pystore/__init__.py
pystore/collection.py
pystore/config.py
pystore/item.py
pystore/store.py
pystore/utils.py
PyStore-0.1.24.dist-info/LICENSE.txt
PyStore-0.1.24.dist-info/METADATA
PyStore-0.1.24.dist-info/WHEEL
PyStore-0.1.24.dist-info/entry_points.txt
PyStore-0.1.24.dist-info/top_level.txt
PyStore-0.1.24.dist-info/RECORD
