Metadata-Version: 2.1
Name: PyStore
Version: 0.1.24
Summary: Fast data store for Pandas timeseries data
Home-page: https://github.com/ranaroussi/pystore
Author: Ran Aroussi
Author-email: ran@aroussi.com
License: Apache Software License
Keywords: dask,datastore,flatfile,pystore
Platform: linux
Platform: unix
Platform: macOS
Classifier: License :: OSI Approved :: Apache Software License
Classifier: Development Status :: 5 - Production/Stable
Classifier: Operating System :: OS Independent
Classifier: Intended Audience :: Developers
Classifier: Topic :: Database
Classifier: Topic :: Database :: Database Engines/Servers
Classifier: Topic :: Software Development :: Libraries
Classifier: Topic :: Software Development :: Libraries :: Python Modules
Classifier: Programming Language :: Python :: 2.7
Classifier: Programming Language :: Python :: 3.5
Classifier: Programming Language :: Python :: 3.6
Classifier: Programming Language :: Python :: 3.7
Classifier: Programming Language :: Python :: 3.8
Classifier: Programming Language :: Python :: 3.9
License-File: LICENSE.txt
Requires-Dist: python-snappy
Requires-Dist: multitasking
Requires-Dist: toolz
Requires-Dist: partd
Requires-Dist: cloudpickle
Requires-Dist: distributed
Requires-Dist: pandas
Requires-Dist: numpy
Requires-Dist: pyarrow
Requires-Dist: dask[dataframe]
